yamer/__init__.py
yamer/convertor.py
yaml2txt-1.3.dist-info/METADATA
yaml2txt-1.3.dist-info/WHEEL
yaml2txt-1.3.dist-info/top_level.txt
yaml2txt-1.3.dist-info/RECORD
