Metadata-Version: 2.1
Name: yaml2txt
Version: 1.3
Summary: Framework for converting .yaml or .yml file to text file
Home-page: https://johnnes-smarts.ch
Author: David Johnnes
Author-email: david.johnnes@gmail.com
License: License :: OSI Approved :: MIT License
Keywords: DevOps,Audit Automation,Audit Orchestration,Vendor-Neutral configurations Audit
Platform: UNKNOWN
Classifier: Programming Language :: Python :: 3
Classifier: License :: OSI Approved :: MIT License
Classifier: Operating System :: OS Independent
